{
  "domain": "johnlewis.com",
  "enriched_at": "2026-02-26T03:12:30.413996",
  "builtwith": {
    "all_techs": [
      "DAV",
      "Viewport Meta",
      "StarHub",
      "Amazon Mumbai Region",
      "jQuery CDN",
      "Numberly",
      "Akamai SSL",
      "CloudFront",
      "Cloudflare Radar Top 50k",
      "Optimost",
      "Amazon Frankfurt Region",
      "Instagram",
      "Edge Network",
      "Stumbleupon",
      "Bazaarvoice",
      "MasterCard",
      "Singaporean Server Location",
      "Google Adsense",
      "OpenSSL",
      "Kibo",
      "Yieldlab",
      "RichRelevance Apps",
      "Japanese Yen",
      "Ascio Technologies",
      "jsPDF",
      "Citrix NetScaler",
      "JavaScript Modules",
      "Vodafone Europe",
      "Fastly",
      "Endeca",
      "Yahoo Dot",
      "YouTube",
      "GoDaddy Parking",
      "YouTube Link",
      "Google Plus One Button",
      "Australian English HREF LANG",
      "EU VAT Registration",
      "Cloudflare Radar",
      "CrUX Top 10m",
      "Hammer JS",
      "Adobe ColdFusion",
      "Microsoft Azure DNS",
      "Twitter",
      "Google Maps for Work",
      "Facebook Pixel",
      "Teads",
      "Underdog Media",
      "jQuery 2.1.4",
      "Yield Manager",
      "jQuery 3.6.0"
    ],
    "tech_categories": {
      "widgets": [
        "Stumbleupon",
        "Yahoo Bookmarklet",
        "Twitter Tweet Button",
        "Google Plus One Button",
        "Google Plus One Platform",
        "Facebook Like Button",
        "Twitter Timeline",
        "Google Font API",
        "Microdata for Google Shopping",
        "Imgix",
        "European Commission Online Dispute Resolution",
        "Facebook Sharer",
        "Cloudflare Bot Manager",
        "Smart App Banner",
        "Facebook Like",
        "ServiceTick",
        "Lijit Widget",
        "Ensighten",
        "QuBit OpenTag",
        "Salesforce Live Agent",
        "Google Tag Manager",
        "Pinterest",
        "Akamai Bot Manager",
        "EU VAT Registration",
        "COVID-19",
        "United Kingdom VAT Registration",
        "Taggstar",
        "Verisign Seal",
        "Confirmit",
        "Apple Whitelist",
        "Slack",
        "CrUX Dataset",
        "CrUX Top 5000",
        "Cloudflare Radar",
        "Cloudflare Radar Top 50k",
        "Global Privacy Control",
        "US Privacy User Signal Mechanism",
        "Financial Conduct Authority",
        "About Cookies",
        "Network Advertising Initiative",
        "Fit Analytics",
        "CommonCrawl Top 10k",
        "Cloudflare Radar Top 100k",
        "Common Crawl",
        "CommonCrawl Top 100k",
        "Microdata for Google Shopping",
        "Google Plus One Button",
        "Google Plus One Platform",
        "Twitter Tweet Button",
        "Amazon Elastic Load Balancing Sticky Session",
        "Amazon Elastic Load Balancing Sticky Session",
        "Amazon Elastic Load Balancing Sticky Session",
        "Amazon Elastic Load Balancing Sticky Session",
        "Amazon Elastic Load Balancing Sticky Session",
        "Amazon Elastic Load Balancing Sticky Session",
        "Amazon Elastic Load Balancing Sticky Session",
        "Amazon Elastic Load Balancing Sticky Session",
        "Amazon Elastic Load Balancing Sticky Session",
        "Amazon Elastic Load Balancing Sticky Session",
        "Amazon Elastic Load Balancing Sticky Session",
        "Amazon Elastic Load Balancing Sticky Session",
        "Amazon Elastic Load Balancing Sticky Session",
        "Amazon Elastic Load Balancing Sticky Session",
        "Amazon Elastic Load Balancing Sticky Session",
        "Amazon Elastic Load Balancing Sticky Session",
        "Amazon Elastic Load Balancing Sticky Session",
        "Amazon Elastic Load Balancing Sticky Session",
        "Amazon Elastic Load Balancing Sticky Session",
        "Amazon Elastic Load Balancing Sticky Session",
        "Amazon Elastic Load Balancing Sticky Session",
        "Amazon Elastic Load Balancing Sticky Session",
        "Amazon Elastic Load Balancing Sticky Session",
        "Amazon Elastic Load Balancing Sticky Session",
        "Amazon Elastic Load Balancing Sticky Session",
        "Amazon Elastic Load Balancing Sticky Session",
        "Amazon Elastic Load Balancing Sticky Session",
        "Amazon Elastic Load Balancing Sticky Session",
        "Amazon Elastic Load Balancing Sticky Session",
        "Amazon Elastic Load Balancing Sticky Session",
        "Amazon Elastic Load Balancing Sticky Session",
        "Amazon Elastic Load Balancing Sticky Session",
        "Amazon Elastic Load Balancing Sticky Session",
        "Amazon Elastic Load Balancing Sticky Session",
        "Amazon Elastic Load Balancing Sticky Session",
        "Bugsnag",
        "CrUX Top 5m",
        "Typekit",
        "Intercom",
        "Ticketfly",
        "Google Font API",
        "Jetboost",
        "CrUX Top 1m",
        "CrUX Top 5m",
        "Cloudflare Bot Manager",
        "CrUX Top 500k",
        "Universe",
        "OneTrust",
        "CrUX Top 100k",
        "Amazon Elastic Load Balancing Sticky Session",
        "CrUX Top 50k",
        "DigiCert",
        "CrUX Top 500k",
        "CrUX Top 1m",
        "TurboLinks",
        "reCAPTCHA v3",
        "reCAPTCHA",
        "Typekit",
        "CrUX Top 5m",
        "CrUX Top 5m",
        "CrUX Top 500k",
        "CrUX Top 1m",
        "CrUX Top 10m",
        "CrUX Top 50m",
        "CrUX Top 5m",
        "CrUX Top 10m",
        "CrUX Top 50m",
        "CrUX Top 5m",
        "Font Awesome",
        "Imperva Bot Detection and Mitigation",
        "CrUX Top 50m",
        "CrUX Top 10m",
        "Imperva Bot Detection and Mitigation"
      ],
      "javascript": [
        "Twitter Platform",
        "Google API",
        "Modernizr 1.7",
        "Stickyfill",
        "Day.js",
        "Polyfill IO",
        "MobX",
        "HTML5 History API",
        "jQuery",
        "SWFObject",
        "Facebook for Websites",
        "yepnope",
        "html5shiv",
        "jQuery 1.11.0",
        "jQuery NoConflict",
        "matchMedia",
        "Respond",
        "Facebook SDK",
        "Modernizr",
        "React",
        "es6 promise",
        "Handlebars",
        "core-js",
        "lodash",
        "Lightbox",
        "Webpack",
        "Classnames",
        "Moment JS",
        "Babel",
        "Web Components",
        "Hammer JS",
        "Intersection Observer",
        "Google Hosted Libraries",
        "Google Hosted jQuery",
        "jQuery 1.4.2",
        "jQuery 1.5.1",
        "React Redux",
        "JavaScript Modules",
        "jQuery 1.6.2",
        "Twitter Platform",
        "Google API",
        "Modernizr 1.7",
        "Vue",
        "Lightning.js",
        "Sentry",
        "jQuery 3.6.0",
        "jsPDF",
        "jQuery 2.1.4",
        "html2canvas",
        "RequireJS",
        "Swiper",
        "Angular JS",
        "Raven JS",
        "Sentry",
        "WebFont Loader",
        "Google Hosted Web Font Loader",
        "Underscore.js",
        "jQuery 3.5.1",
        "Select2",
        "Slick JS",
        "Almond",
        "Backbone.js",
        "Yahoo User Interface",
        "Day.js",
        "Google Hosted jQuery UI",
        "jQuery UI",
        "jQuery 3.5.1",
        "jQuery Cookie",
        "Select2",
        "Almond",
        "RequireJS",
        "jQuery 1.10.2",
        "jQuery UI",
        "SweetAlert",
        "jQuery UI Mouse"
      ],
      "cdn": [
        "GStatic Google Static Content",
        "CDN JS",
        "Cloudflare",
        "Cloudflare JS",
        "Akamai",
        "CloudFront",
        "AJAX Libraries API",
        "UNPKG",
        "Akamai Global Host",
        "GStatic Google Static Content",
        "GStatic Google Static Content",
        "Fastly CDN",
        "GStatic Google Static Content",
        "GoDaddy CDN",
        "Level3",
        "Akamai Global Host",
        "Cloudinary",
        "Akamai Global Host",
        "Fastly CDN",
        "CDN JS",
        "Cloudflare JS",
        "Amazon S3",
        "Filestack",
        "UNPKG",
        "Cloudinary",
        "jsDelivr",
        "OSS CDN",
        "jQuery CDN",
        "Cloudflare"
      ],
      "payment": [
        "Visa",
        "MasterCard",
        "Maestro",
        "Google Pay",
        "Pound Sterling",
        "Japanese Yen",
        "Euro",
        "American Express",
        "Klarna",
        "Square",
        "Klarna Checkout",
        "Stripe",
        "Stripe",
        "Stripe v3",
        "Braintree",
        "Google Pay",
        "MasterCard",
        "Afterpay",
        "PayPal"
      ],
      "analytics": [
        "Twitter Analytics",
        "Content Square",
        "SessionCam",
        "Optimost",
        "Bazaarvoice",
        "Facebook Domain Insights",
        "Google Analytics",
        "DoubleClick Floodlight",
        "Omniture SiteCatalyst",
        "TagMan",
        "Adobe Dynamic Tag Management",
        "Yahoo Web Analytics",
        "Datalogix",
        "Rapleaf",
        "Bubblestat",
        "Google Conversion Tracking",
        "New Relic",
        "eDigitalResearch",
        "Monetate",
        "Lotame Crowd Control",
        "MediaMath",
        "Yahoo Dot",
        "LiveRamp",
        "Adscale",
        "Facebook Signal",
        "Qubit Deliver",
        "Adobe Marketing Cloud",
        "Global Site Tag",
        "Twitter Website Universal Tag",
        "Twitter Conversion Tracking",
        "Bing Universal Event Tracking",
        "Visual IQ",
        "Salesforce",
        "Sitestat",
        "Google Analytics Classic",
        "Google Analytics 4",
        "Google Universal Analytics",
        "Google Analytics Enhanced Link Attribution",
        "Usablenet",
        "Digital Window",
        "Ravelin",
        "Matomo",
        "Trustpilot",
        "Usabilla",
        "Facebook Pixel",
        "Facebook Conversion Tracking",
        "CrazyEgg",
        "Google Conversion Linker",
        "Google AdWords Conversion",
        "Fastly",
        "Segment",
        "Fastly",
        "FullStory",
        "Fastly",
        "Dynatrace RUM",
        "iovation",
        "Akamai Page Integrity Manager",
        "Klaviyo"
      ],
      "mapping": [
        "Google Maps for Work",
        "Google Maps API",
        "Google Maps"
      ],
      "media": [
        "iSiteTV",
        "YouTube",
        "Quicktime",
        "FlixMedia"
      ],
      "framework": [
        "Express",
        "Person Schema",
        "LocalBusiness Schema",
        "PostalAddress Schema",
        "Shockwave Flash Embed",
        "ASP.NET Ajax",
        "ASP.NET",
        "PHP",
        "Java EE",
        "Perl",
        "Google Front End",
        "Adobe Enterprise Cloud",
        "Adobe ColdFusion",
        "ContactPoint Schema",
        "Organization Schema",
        "Facebook Domain Verification",
        "Microsoft Frontpage",
        "Visual Studio",
        "Choices",
        "Subversion",
        "Next.js",
        "DAV",
        "AggregateRating Schema",
        "Brand Schema",
        "Offer Schema",
        "Product Schema",
        "Ruby on Rails Token",
        "Ruby on Rails",
        "OpenResty",
        "ASP.NET 4.0",
        "ASP.NET 4.0",
        "Google Cloud Functions",
        "Express",
        "OpenResty",
        "Ruby on Rails Token",
        "Heroku Vegur Proxy",
        "ASP.NET 4.0",
        "ASP.NET MVC",
        "ASP.NET 4.0"
      ],
      "cms": [
        "papaya CMS",
        "Yext",
        "Endeca",
        "Adobe CQ",
        "Adobe Scene7",
        "My Salesforce",
        "Craft",
        "Contentful",
        "Webflow",
        "Finsweet",
        "Logicalware"
      ],
      "cdns": [
        "AWS Cloudfront Paris Edge",
        "AWS Cloudfront London Edge",
        "Cloudflare CDN",
        "Akamai Edge",
        "Akamai EdgeWorkers",
        "Google Cloud CDN",
        "Amazon S3 CDN",
        "Cloudflare CDN",
        "Akamai Global Request Number",
        "Google Cloud CDN",
        "Cloudflare CDN"
      ],
      "language": [
        "German - Inferred",
        "English HREF LANG",
        "Irish English HREF LANG",
        "Australian English HREF LANG",
        "New Zealand English HREF LANG",
        "South African English HREF LANG",
        "English - Inferred",
        "French - Inferred"
      ],
      "Web Server": [
        "Apache 2.0",
        "Citrix NetScaler",
        "H2O Webserver",
        "nginx",
        "Varnish",
        "Apache Traffic Server",
        "Application Request Routing",
        "Google Web Server",
        "Jetty",
        "Yet Another Web Server",
        "Microsoft Personal Web Server",
        "NCSA HTTPd",
        "nginx 0.8",
        "Apache",
        "Apache",
        "Apache",
        "Apache 2.4",
        "Apache",
        "Rack Cache",
        "Apache",
        "IIS",
        "IIS 7",
        "IIS",
        "IIS 7",
        "Apache",
        "Nginx 1.16",
        "AWS Lambda",
        "Varnish 4.x",
        "Cowboy",
        "BIG-IP",
        "IIS",
        "IIS 10"
      ],
      "ads": [
        "AppNexus",
        "Infectious Media",
        "Rich Relevance",
        "DoubleClick.Net",
        "Openads/OpenX",
        "Switch Ads",
        "Pubmatic",
        "Rubicon Project",
        "Yield Manager",
        "Improve Digital",
        "Yahoo Small Business",
        "myThings",
        "Google Adsense",
        "AppNexus Segment Pixel",
        "IponWeb BidSwitch",
        "Criteo",
        "Facebook Exchange FBX",
        "Advantage Media",
        "ADTECH",
        "AOL-Time Warner Online Advertising",
        "Open AdStream",
        "ContextWeb",
        "Underdog Media",
        "ad6media",
        "RichRelevance Apps",
        "Tapad",
        "BlueKai DMP",
        "BlueKai",
        "LiveRail",
        "Adify",
        "Burst Media",
        "Index Exchange",
        "1000mercis",
        "TripleLift",
        "Crosswise",
        "Drawbridge",
        "Facebook Custom Audiences",
        "Criteo OneTag",
        "AMob",
        "Yieldlab",
        "Omnitag",
        "Taboola",
        "eXelate",
        "Teads",
        "Google Remarketing",
        "ECustomer Opinions",
        "Weborama",
        "DoubleClick Bid Manager",
        "Twitter Ads",
        "ExactTarget",
        "Snap Pixel",
        "Numberly",
        "Google Floodlight Sales",
        "Google Floodlight Counter",
        "Google Adsense for Domains",
        "AdBlock Acceptable Ads"
      ],
      "ssl": [
        "Verisign EV",
        "Verisign EV SGC",
        "Symantec VeriSign",
        "SSL by Default",
        "DigiCert SSL",
        "DigiCert EV",
        "HSTS",
        "GlobalSign",
        "Google SSL",
        "LetsEncrypt",
        "LetsEncrypt",
        "Common Name Invalid",
        "HSTS IncludeSubdomains PreLoad",
        "Common Name Invalid",
        "Akamai SSL",
        "Amazon SSL",
        "HSTS IncludeSubdomains PreLoad",
        "Common Name Invalid",
        "LetsEncrypt",
        "Google SSL",
        "LetsEncrypt",
        "Google SSL",
        "LetsEncrypt"
      ],
      "Web Master": [
        "MSN/Bing Webmaster",
        "Google Webmaster",
        "Yahoo Site Explorer"
      ],
      "mx": [
        "SPF",
        "Salesforce SPF",
        "Oracle CX",
        "SocketLabs",
        "DMARC",
        "ExactTarget Email",
        "FirstData",
        "EmailOnDeck",
        "DMARC None",
        "Apple iCloud Mail",
        "Amazon SES",
        "Sender ID",
        "MailChimp SPF",
        "GoDaddy Email",
        "Sender ID",
        "Proofpoint",
        "Microsoft Azure DNS"
      ],
      "mobile": [
        "Viewport Meta",
        "Mobile Non Scaleable Content",
        "Apple Mobile Web Clips Icon",
        "IPhone / Mobile Compatible",
        "Apple Mobile Web App Capable",
        "Apple Mobile Web App Status Bar Style"
      ],
      "CDN": [
        "Content Delivery Network"
      ],
      "shipping": [
        "Royal Mail",
        "DHL",
        "TNT"
      ],
      "hosting": [
        "Akamai Hosted",
        "IP Block Owner",
        "StarHub",
        "Edge Network",
        "Singaporean Server Location",
        "Telecom Argentina",
        "Cloudflare Hosting",
        "Australian Server Location",
        "Swedish Server Location",
        "German Server Location",
        "U.S. Server Location",
        "403 Error",
        "Spanish Server Location",
        "Amazon",
        "Domain Not Resolving",
        "Softlayer",
        "NTT America",
        "TM Net",
        "German Server Location",
        "Amazon",
        "Amazon Ireland Region",
        "Google",
        "Google Cloud",
        "Fastly Hosted",
        "Fastly Load Balancer",
        "Google App Engine",
        "U.S. Server Location",
        "Amazon",
        "Amazon Ireland Region",
        "AWS Global Accelerator",
        "U.S. Server Location",
        "GoDaddy",
        "Google Cloud",
        "Google",
        "Google Cloud Global Multi-Region",
        "Liquid Web",
        "Linode",
        "U.S. Server Location",
        "Amazon Elastic Load Balancing",
        "Amazon",
        "Amazon Ireland Region",
        "Amazon ELB Ireland",
        "Irish Server Location",
        "CenturyLink",
        "Level 3 Communications",
        "U.S. Server Location",
        "TM Net",
        "U.S. Server Location",
        "Turkish Server Location",
        "Greek Server Location",
        "LG U Plus",
        "NTT America",
        "U.S. Server Location",
        "Spanish Server Location",
        "Italian Server Location",
        "Hong Kong Server Location",
        "French Server Location",
        "U.S. Server Location",
        "Indian Server Location",
        "Italian Server Location",
        "Amazon",
        "Domain Not Resolving",
        "U.S. Server Location",
        "Fastly Hosted",
        "Amazon",
        "Amazon Ireland Region",
        "Google Cloud",
        "Google",
        "Amazon",
        "Amazon Ireland Region",
        "Amazon Tokyo Region",
        "Amazon Virginia Region",
        "Amazon Oregon Region",
        "Webflow Hosting",
        "Amazon Sydney Region",
        "Amazon Mumbai Region",
        "Amazon Paris Region",
        "Amazon Stockholm Region",
        "Google Cloud Global Multi-Region",
        "U.S. Server Location",
        "Italian Server Location",
        "Turkish Server Location",
        "Google",
        "Domain Not Resolving",
        "U.S. Server Location",
        "Turkish Server Location",
        "French Server Location",
        "Indian Server Location",
        "German Server Location",
        "U.S. Server Location",
        "Hong Kong Server Location",
        "Google Cloud",
        "Google",
        "Google Cloud Global Multi-Region",
        "U.S. Server Location",
        "Amazon",
        "Amazon Ireland Region",
        "U.S. Server Location",
        "Spanish Server Location",
        "Indian Server Location",
        "U.S. Server Location",
        "U.S. Server Location",
        "Amazon",
        "Amazon Ireland Region",
        "Irish Server Location",
        "Amazon",
        "British Server Location",
        "Amazon",
        "Amazon Ohio Region",
        "Amazon Frankfurt Region",
        "Amazon Sydney Region",
        "Amazon Oregon Region",
        "Amazon California Region",
        "CenturyLink",
        "Level 3 Communications",
        "U.S. Server Location",
        "Amazon",
        "U.S. Server Location",
        "Vodafone Europe",
        "Cloudflare Network Error Logging",
        "British Server Location",
        "British Server Location",
        "British Server Location",
        "British Server Location",
        "British Server Location",
        "British Server Location",
        "U.S. Server Location",
        "British Server Location",
        "British Server Location",
        "British Server Location",
        "French Server Location"
      ],
      "ns": [
        "Akamai DNS",
        "3 to 9 ccTLD Redirects",
        "Amazon Route 53",
        "DNSSEC",
        "DNSSEC",
        "DNSSEC",
        "DNSSEC",
        "DNSSEC",
        "DNSSEC",
        "DNSSEC",
        "DNSSEC",
        "DNSSEC",
        "DNSSEC",
        "DNSSEC",
        "DNSSEC",
        "DNSSEC",
        "DNSSEC",
        "DNSSEC",
        "DNSSEC",
        "DNSSEC",
        "DNSSEC",
        "DNSSEC",
        "DNSSEC",
        "DNSSEC",
        "DNSSEC",
        "DNSSEC",
        "DNSSEC",
        "DNSSEC",
        "DNSSEC",
        "DNSSEC",
        "DNSSEC",
        "DNSSEC",
        "DNSSEC",
        "DNSSEC",
        "DNSSEC",
        "DNSSEC",
        "DNSSEC",
        "DNSSEC",
        "GoDaddy DNS",
        "ParkLogic DNS",
        "DNSSEC",
        "DNSSEC",
        "DNSSEC",
        "Amazon Route 53",
        "DNSSEC",
        "DNSSEC",
        "DNSSEC",
        "Heroku DNS",
        "DNSSEC",
        "DNSSEC",
        "DNSSEC",
        "DNSSEC",
        "DNSSEC",
        "DNSSEC",
        "DNSSEC"
      ],
      "copyright": [
        "Copyright Year 2001",
        "Copyright Year 2017"
      ],
      "shop": [
        "Kibo",
        "Oracle Commerce"
      ],
      "link": [
        "Events Page",
        "Facebook",
        "Twitter",
        "LinkedIn",
        "Instagram",
        "TikTok",
        "Accessibility Statement",
        "Plans and Pricing",
        "Sustainability",
        "Members Page",
        "Google Play Store Link",
        "YouTube Link",
        "GitHub",
        "Modern Slavery Statement",
        "Artificial Intelligence",
        "SaaS Pricing in Pounds",
        "SaaS Pricing Above $800 Per Month",
        "Companies House",
        "Find a Store",
        "Apple App Link",
        "X",
        "EDAA",
        "Pre Year 2000",
        "Human Rights Policy",
        "Wikipedia",
        "X",
        "Zendesk Link"
      ],
      "robots": [
        "Sogou Bot Disallow",
        "Some Robots Disallow",
        "Robots Disallow",
        "Robots Disallow",
        "Robots Disallow",
        "Robots Disallow",
        "Robots Disallow",
        "Robots Disallow",
        "Robots Disallow",
        "Robots Disallow",
        "Robots Disallow",
        "Robots Disallow",
        "Robots Disallow"
      ],
      "Server": [
        "Envoy",
        "IPv6",
        "IPv6",
        "Limiter Modules",
        "OpenSSL",
        "CentOS",
        "IPv6",
        "IPv6",
        "Squid"
      ],
      "registrar": [
        "Ascio Technologies"
      ],
      "parked": [
        "GoDaddy Parking",
        "Park Logic"
      ],
      "feeds": [
        "RSS"
      ]
    },
    "has_algolia": false,
    "search_providers": [
      "Amazon Elastic Load Balancing",
      "Amazon Elastic Load Balancing Sticky Session"
    ],
    "tech_count": 516
  },
  "similarweb": {
    "monthly_visits": 30087276.57004118,
    "global_rank": [
      {
        "date": "2026-02",
        "global_rank": 1626
      }
    ],
    "country_rank": null,
    "category": null,
    "competitors": [
      "argos.co.uk",
      "currys.co.uk",
      "amazon.co.uk",
      "houseoffraser.co.uk",
      "very.co.uk",
      "ebay.co.uk",
      "etsy.com",
      "boots.com",
      "next.co.uk",
      "marksandspencer.com"
    ],
    "top_countries": []
  },
  "competitors": {
    "competitor_tech": {
      "argos.co.uk": {
        "search_providers": [
          "BloomReach",
          "Amazon Elastic Load Balancing Sticky Session"
        ],
        "has_algolia": false,
        "tech_count": 479
      },
      "currys.co.uk": {
        "search_providers": [
          "Algolia",
          "Amazon Elastic Load Balancing Sticky Session"
        ],
        "has_algolia": true,
        "tech_count": 527
      },
      "houseoffraser.co.uk": {
        "search_providers": [
          "Algolia",
          "BloomReach"
        ],
        "has_algolia": true,
        "tech_count": 517
      },
      "very.co.uk": {
        "search_providers": [
          "Amazon Elastic Load Balancing Sticky Session"
        ],
        "has_algolia": false,
        "tech_count": 504
      }
    },
    "algolia_competitors": [
      "currys.co.uk",
      "houseoffraser.co.uk"
    ],
    "competitors_checked": 4
  }
}