{
  "domain": "robertdyas.co.uk",
  "enriched_at": "2026-02-26T06:05:22.306205",
  "version": "2.0",
  "builtwith": {
    "tech_count": 427,
    "all_techs": [
      "WordPress",
      "selectivizr",
      "Companies House",
      "jQuery",
      "Yahoo Small Business",
      "Cloudflare Radar Top 50k",
      "Amazon CloudFront",
      "Atlas",
      "SSL by Default",
      "Yieldlab",
      "Twiago",
      "DHL",
      "Facebook Like",
      "Amazon SSL",
      "Adalyser",
      "SizzleJS",
      "MailChimp",
      "The Trade Desk",
      "RSS",
      "Trustpilot",
      "United Kingdom VAT Registration",
      "Enquire JS",
      "DMARC None",
      "Content Delivery Network",
      "AWS Cloudfront Mumbai Edge",
      "reCAPTCHA v2",
      "Cloudflare Radar",
      "403 Error",
      "Fastly Hosted",
      "Rapleaf",
      "KnockoutJS",
      "Magento 2 Enterprise",
      "Improve Digital",
      "Burst Media",
      "AWS Cloudfront Marseille Edge",
      "Offer Schema",
      "Google Remarketing",
      "Google Adsense",
      "Sendgrid",
      "MLN Advertising",
      "Copyright Year 2013",
      "Prototype",
      "Slick JS",
      "WebTrends",
      "script.aculo.us",
      "CrUX Dataset",
      "Visa",
      "AWS Cloudfront Paris Edge",
      "Facebook Like Button",
      "jQuery 1.9.1",
      "html5shiv",
      "PayPal Button",
      "ScarabResearch",
      "Royal Mail",
      "GeoTrust EV",
      "eXelate",
      "Cloudflare Challenge",
      "Pound Sterling",
      "Nativo",
      "DoubleClick Floodlight",
      "AWS Cloudfront Milan Edge",
      "Centro",
      "JavaScript Modules",
      "Flashtalking",
      "Google Analytics Enhanced Ecommerce",
      "GitHub",
      "Careers",
      "Magnific Popup",
      "Global Site Tag",
      "Google Analytics 4",
      "Cloudflare Network Error Logging",
      "BloomReach",
      "Modernizr 2.6",
      "Yahoo Web Analytics",
      "Rubicon Project",
      "YouTube IFrame Upload",
      "U.S. Server Location",
      "UNiDAYS",
      "AWS Cloudfront New York NY Edge",
      "Google Plus One Button",
      "YouTube IFrame API",
      "Gender Pay Gap Report",
      "Taboola",
      "RequireJS",
      "AppNexus Segment Pixel",
      "jQuery Colorbox",
      "Font Awesome",
      "SpotXchange",
      "Facebook Custom Audiences",
      "AOL-Time Warner Online Advertising",
      "Service Worker",
      "Google AdWords Conversion",
      "Twitter",
      "Java EE",
      "Accuen",
      "CommonCrawl Top 5m",
      "FLoC Opt-Out",
      "CommonCrawl Top 500k",
      "Google Conversion Linker",
      "Apple Mobile Web Clips Icon"
    ],
    "search_providers": [
      "Amazon Elastic Load Balancing",
      "BloomReach"
    ],
    "has_algolia": false
  },
  "similarweb": {
    "monthly_visits": null,
    "global_rank": null,
    "competitors": []
  },
  "financials": {
    "is_public": false,
    "ticker": null
  },
  "hiring": {
    "has_careers_page": false,
    "hiring_signals": []
  },
  "competitors": {},
  "opportunity_score": {
    "score": 45,
    "factors": [
      "No Algolia (greenfield)",
      "Displacement opportunity (BloomReach)"
    ],
    "recommendation": "WARM"
  }
}